{"named_endpoints":{"/create_or_update_file":{"parameters":[{"label":"Repository ID","parameter_name":"repo_id","parameter_has_default":false,"parameter_default":null,"type":{"type":"string"},"python_type":{"type":"str","description":""},"component":"Textbox","example_input":"Hello!!"},{"label":"Path in Repo","parameter_name":"path_in_repo","parameter_has_default":false,"parameter_default":null,"type":{"type":"string"},"python_type":{"type":"str","description":""},"component":"Textbox","example_input":"Hello!!"},{"label":"Content","parameter_name":"content","parameter_has_default":false,"parameter_default":null,"type":{"type":"string"},"python_type":{"type":"str","description":""},"component":"Textbox","example_input":"Hello!!"}],"returns":[{"label":"Result","type":{"type":{},"description":"any valid json"},"python_type":{"type":"str | float | bool | list | dict","description":"any valid json"},"component":"Json"}],"api_visibility":"public","description":""},"/list_repo_files":{"parameters":[{"label":"Repository ID","parameter_name":"repo_id","parameter_has_default":false,"parameter_default":null,"type":{"type":"string"},"python_type":{"type":"str","description":""},"component":"Textbox","example_input":"Hello!!"}],"returns":[{"label":"Result","type":{"type":{},"description":"any valid json"},"python_type":{"type":"str | float | bool | list | dict","description":"any valid json"},"component":"Json"}],"api_visibility":"public","description":""},"/get_status":{"parameters":[],"returns":[{"label":"value_14","type":{"type":"string"},"python_type":{"type":"str","description":""},"component":"Textbox"}],"api_visibility":"public","description":""}},"unnamed_endpoints":{}}